setup.cfg
setup.py
cmdr/__init__.py
cmdr/cmdr.py
cmdr/repl.py
pycmdr.egg-info/PKG-INFO
pycmdr.egg-info/SOURCES.txt
pycmdr.egg-info/dependency_links.txt
pycmdr.egg-info/requires.txt
pycmdr.egg-info/top_level.txt